aea_cli_ipfs/__init__.py
aea_cli_ipfs/core.py
aea_cli_ipfs/ipfs_utils.py
aea_cli_ipfs-1.0.4.dist-info/LICENSE
aea_cli_ipfs-1.0.4.dist-info/METADATA
aea_cli_ipfs-1.0.4.dist-info/WHEEL
aea_cli_ipfs-1.0.4.dist-info/entry_points.txt
aea_cli_ipfs-1.0.4.dist-info/top_level.txt
aea_cli_ipfs-1.0.4.dist-info/RECORD
