Metadata-Version: 2.1
Name: aea-cli-ipfs
Version: 1.0.4
Summary: CLI extension for AEA framework wrapping IPFS functionality.
Author: Fetch.AI Limited
License: Apache-2.0
Classifier: Environment :: Console
Classifier: Environment :: Web Environment
Classifier: Development Status :: 5 - Production/Stable
Classifier: Intended Audience :: Developers
Classifier: License :: OSI Approved :: Apache Software License
Classifier: Natural Language :: English
Classifier: Operating System :: MacOS
Classifier: Operating System :: Microsoft
Classifier: Operating System :: Unix
Classifier: Programming Language :: Python :: 3.6
Classifier: Programming Language :: Python :: 3.7
Classifier: Programming Language :: Python :: 3.8
Classifier: Programming Language :: Python :: 3.9
Classifier: Topic :: Communications
Classifier: Topic :: Internet
Classifier: Topic :: Software Development
License-File: LICENSE
Requires-Dist: aea (<2.0.0,>=1.0.0)
Requires-Dist: ipfshttpclient (==0.8.0a2)
